odoo8_addon_mrp_operations_extension-8.0.2.0.1-py2.7-nspkg.pth
odoo8_addon_mrp_operations_extension-8.0.2.0.1.dist-info/METADATA
odoo8_addon_mrp_operations_extension-8.0.2.0.1.dist-info/RECORD
odoo8_addon_mrp_operations_extension-8.0.2.0.1.dist-info/WHEEL
odoo8_addon_mrp_operations_extension-8.0.2.0.1.dist-info/namespace_packages.txt
odoo8_addon_mrp_operations_extension-8.0.2.0.1.dist-info/top_level.txt
odoo_addons/mrp_operations_extension/README.rst
odoo_addons/mrp_operations_extension/__init__.py
odoo_addons/mrp_operations_extension/__openerp__.py
odoo_addons/mrp_operations_extension/hooks.py
odoo_addons/mrp_operations_extension/data/mrp_operations_extension_data.xml
odoo_addons/mrp_operations_extension/demo/hr_employee_demo.xml
odoo_addons/mrp_operations_extension/demo/mrp_bom_demo.xml
odoo_addons/mrp_operations_extension/demo/mrp_production_demo.xml
odoo_addons/mrp_operations_extension/demo/mrp_routing_demo.xml
odoo_addons/mrp_operations_extension/demo/mrp_workcenter_demo.xml
odoo_addons/mrp_operations_extension/demo/res_partner_demo.xml
odoo_addons/mrp_operations_extension/i18n/am.po
odoo_addons/mrp_operations_extension/i18n/ar.po
odoo_addons/mrp_operations_extension/i18n/bg.po
odoo_addons/mrp_operations_extension/i18n/bs.po
odoo_addons/mrp_operations_extension/i18n/ca.po
odoo_addons/mrp_operations_extension/i18n/ca_ES.po
odoo_addons/mrp_operations_extension/i18n/cs.po
odoo_addons/mrp_operations_extension/i18n/da.po
odoo_addons/mrp_operations_extension/i18n/de.po
odoo_addons/mrp_operations_extension/i18n/el_GR.po
odoo_addons/mrp_operations_extension/i18n/en_AU.po
odoo_addons/mrp_operations_extension/i18n/en_GB.po
odoo_addons/mrp_operations_extension/i18n/en_US.po
odoo_addons/mrp_operations_extension/i18n/es.po
odoo_addons/mrp_operations_extension/i18n/es_AR.po
odoo_addons/mrp_operations_extension/i18n/es_BO.po
odoo_addons/mrp_operations_extension/i18n/es_CL.po
odoo_addons/mrp_operations_extension/i18n/es_CO.po
odoo_addons/mrp_operations_extension/i18n/es_CR.po
odoo_addons/mrp_operations_extension/i18n/es_DO.po
odoo_addons/mrp_operations_extension/i18n/es_EC.po
odoo_addons/mrp_operations_extension/i18n/es_ES.po
odoo_addons/mrp_operations_extension/i18n/es_MX.po
odoo_addons/mrp_operations_extension/i18n/es_PE.po
odoo_addons/mrp_operations_extension/i18n/es_PY.po
